quantic_rust/__init__.py
quantic_rust/quantic_rust.cpython-311-darwin.so
quantic_rust/utils.py
quantic_rust-0.1.0.dist-info/METADATA
quantic_rust-0.1.0.dist-info/WHEEL
quantic_rust-0.1.0.dist-info/licenses/LICENSE.txt
quantic_rust-0.1.0.dist-info/RECORD
