Metadata-Version: 2.4
Name: quantic-rust
Version: 0.1.0
Classifier: Development Status :: 4 - Beta
Classifier: Intended Audience :: Science/Research
Classifier: Intended Audience :: Developers
Classifier: License :: OSI Approved :: MIT License
Classifier: Operating System :: OS Independent
Classifier: Programming Language :: Python :: 3
Classifier: Programming Language :: Python :: 3.9
Classifier: Programming Language :: Python :: 3.10
Classifier: Programming Language :: Python :: 3.11
Classifier: Programming Language :: Python :: 3.12
Classifier: Programming Language :: Rust
Classifier: Topic :: Scientific/Engineering :: Physics
Classifier: Topic :: Software Development :: Libraries :: Python Modules
Requires-Dist: networkx>=3.0
Requires-Dist: numpy>=1.24.0
Requires-Dist: pytest>=7.0 ; extra == 'dev'
Requires-Dist: maturin>=1.4 ; extra == 'dev'
Provides-Extra: dev
License-File: LICENSE.txt
Summary: High-Performance Quantum Computing Library in Rust with Python bindings
Keywords: quantum,computing,qiskit,cirq,rust,pyo3,quantum-computing,quantum-algorithms
Author-email: Mahir Labib <mdmahirlabib@gmail.com>
Requires-Python: >=3.9
Project-URL: Documentation, https://github.com/Mahir101/quantic-rust#readme
Project-URL: Homepage, https://github.com/Mahir101/quantic-rust
Project-URL: Repository, https://github.com/Mahir101/quantic-rust
